core/__init__.py
core/test_c_code.py
quadkey/quadkey/core/utils.cpython-38-x86_64-linux-gnu.so
quadkey_boosted-1.0.4.dist-info/WHEEL
quadkey_boosted-1.0.4.dist-info/entry_points.txt
quadkey_boosted-1.0.4.dist-info/METADATA
quadkey_boosted-1.0.4.dist-info/RECORD
quadkey_boosted-1.0.4.dist-info/top_level.txt
quadkey_boosted-1.0.4.dist-info/LICENSE
