Metadata-Version: 2.1
Name: quadkey-boosted
Version: 1.0.4
Summary: Python library that provides a powerful set of tools and functions for working with quadkeys. Built on top of C it offers lightning-fast calculations, ensuring optimal performance even with large-scale datasets.
Home-page: https://github.com/ls-da3m0ns/quadkey-boosted
Author: Prashant Singh
Author-email: mail.prashantsingh.41@gmail.com
Project-URL: Documentation, https://github.com/ls-da3m0ns/quadkey-boosted
Project-URL: Source Code, https://github.com/ls-da3m0ns/quadkey-boosted
Project-URL: Bug Tracker, https://github.com/ls-da3m0ns/quadkey-boosted/issues
Classifier: Programming Language :: Python :: 3
Classifier: Operating System :: OS Independent
Classifier: License :: OSI Approved :: Apache Software License
Classifier: Topic :: Scientific/Engineering :: GIS
Classifier: Topic :: Software Development :: Libraries :: Python Modules
Requires-Python: >=3.6
License-File: LICENSE
Requires-Dist: Cython
